{"nodes": [{"id": "guardianes_formularios_app_src_entries_admin_tsx", "label": "admin.tsx", "file_type": "code", "source_file": "guardianes-formularios\\app\\src\\entries\\admin.tsx", "source_location": "L1"}, {"id": "admin_app", "label": "App()", "file_type": "code", "source_file": "guardianes-formularios\\app\\src\\entries\\admin.tsx", "source_location": "L19"}], "edges": [{"source": "guardianes_formularios_app_src_entries_admin_tsx", "target": "react", "relation": "imports_from", "confidence": "EXTRACTED", "source_file": "guardianes-formularios\\app\\src\\entries\\admin.tsx", "source_location": "L1", "weight": 1.0}, {"source": "guardianes_formularios_app_src_entries_admin_tsx", "target": "client", "relation": "imports_from", "confidence": "EXTRACTED", "source_file": "guardianes-formularios\\app\\src\\entries\\admin.tsx", "source_location": "L2", "weight": 1.0}, {"source": "guardianes_formularios_app_src_entries_admin_tsx", "target": "react_query", "relation": "imports_from", "confidence": "EXTRACTED", "source_file": "guardianes-formularios\\app\\src\\entries\\admin.tsx", "source_location": "L3", "weight": 1.0}, {"source": "guardianes_formularios_app_src_entries_admin_tsx", "target": "toast", "relation": "imports_from", "confidence": "EXTRACTED", "source_file": "guardianes-formularios\\app\\src\\entries\\admin.tsx", "source_location": "L4", "weight": 1.0}, {"source": "guardianes_formularios_app_src_entries_admin_tsx", "target": "adminpanel", "relation": "imports_from", "confidence": "EXTRACTED", "source_file": "guardianes-formularios\\app\\src\\entries\\admin.tsx", "source_location": "L5", "weight": 1.0}, {"source": "guardianes_formularios_app_src_entries_admin_tsx", "target": "useinitdata", "relation": "imports_from", "confidence": "EXTRACTED", "source_file": "guardianes-formularios\\app\\src\\entries\\admin.tsx", "source_location": "L6", "weight": 1.0}, {"source": "guardianes_formularios_app_src_entries_admin_tsx", "target": "useauthstore", "relation": "imports_from", "confidence": "EXTRACTED", "source_file": "guardianes-formularios\\app\\src\\entries\\admin.tsx", "source_location": "L7", "weight": 1.0}, {"source": "guardianes_formularios_app_src_entries_admin_tsx", "target": "useyearstore", "relation": "imports_from", "confidence": "EXTRACTED", "source_file": "guardianes-formularios\\app\\src\\entries\\admin.tsx", "source_location": "L8", "weight": 1.0}, {"source": "guardianes_formularios_app_src_entries_admin_tsx", "target": "useappstore", "relation": "imports_from", "confidence": "EXTRACTED", "source_file": "guardianes-formularios\\app\\src\\entries\\admin.tsx", "source_location": "L9", "weight": 1.0}, {"source": "guardianes_formularios_app_src_entries_admin_tsx", "target": "base_css", "relation": "imports_from", "confidence": "EXTRACTED", "source_file": "guardianes-formularios\\app\\src\\entries\\admin.tsx", "source_location": "L10", "weight": 1.0}, {"source": "guardianes_formularios_app_src_entries_admin_tsx", "target": "components_css", "relation": "imports_from", "confidence": "EXTRACTED", "source_file": "guardianes-formularios\\app\\src\\entries\\admin.tsx", "source_location": "L11", "weight": 1.0}, {"source": "guardianes_formularios_app_src_entries_admin_tsx", "target": "admin_app", "relation": "contains", "confidence": "EXTRACTED", "source_file": "guardianes-formularios\\app\\src\\entries\\admin.tsx", "source_location": "L19", "weight": 1.0}]}